{
  "type": "minecraft:block",
  "pools": [
    {
      "rolls": 1,
      "bonus_rolls": 0,
      "entries": [
        {
          "type": "minecraft:item",
          "functions": [
            {
              "function": "minecraft:copy_name",
              "source": "block_entity"
            }
          ],
          "name": "fire_extinguisher:exit_sign_right_down"
        }
      ],
      "conditions": [
        {
          "condition": "minecraft:survives_explosion"
        }
      ]
    }
  ]
}
